LICENSE
MANIFEST.in
README.md
setup.py
Calendar/__init__.py
Calendar/admin.py
Calendar/apps.py
Calendar/models.py
Calendar/tests.py
Calendar/urls.py
Calendar/views.py
Calendar/static/css/bootstrap-datetimepicker.min.css
Calendar/static/css/bootstrap-theme.css
Calendar/static/css/bootstrap-theme.css.map
Calendar/static/css/bootstrap-theme.min.css
Calendar/static/css/bootstrap-theme.min.css.map
Calendar/static/css/bootstrap.css
Calendar/static/css/bootstrap.css.map
Calendar/static/css/bootstrap.min.css
Calendar/static/css/bootstrap.min.css.map
Calendar/static/css/main.css
Calendar/static/fonts/glyphicons-halflings-regular.eot
Calendar/static/fonts/glyphicons-halflings-regular.svg
Calendar/static/fonts/glyphicons-halflings-regular.ttf
Calendar/static/fonts/glyphicons-halflings-regular.woff
Calendar/static/fonts/glyphicons-halflings-regular.woff2
Calendar/static/js/bootstrap-datetimepicker.min.js
Calendar/static/js/bootstrap.js
Calendar/static/js/bootstrap.min.js
Calendar/static/js/jquery.min.js
Calendar/static/js/main.js
Calendar/static/js/moment.min.js
Calendar/static/js/npm.js
Calendar/templates/Calendar/ReadCalendar.html
Calendar/templates/Calendar/WeaklyCalendar.html
Calendar/templatetags/__init__.py
Calendar/templatetags/filters.py
django_weeklycalendar.egg-info/PKG-INFO
django_weeklycalendar.egg-info/SOURCES.txt
django_weeklycalendar.egg-info/dependency_links.txt
django_weeklycalendar.egg-info/top_level.txt