Metadata-Version: 1.1
Name: django-weeklycalendar
Version: 0.1
Summary: Weekly Calendar for Django
Home-page: https://github.com/yvznvr/WeeklyCalendar
Author: Yavuz Unver
Author-email: yvzunver@gmail.com
License: GPL License
Platform: UNKNOWN
Classifier: Environment :: Web Environment
Classifier: Framework :: Django
Classifier: Intended Audience :: Developers
Classifier: Operating System :: OS Independent
Classifier: Programming Language :: Python
Classifier: Programming Language :: Python :: 3.5
Classifier: Programming Language :: Python :: 3.6
Classifier: Topic :: Internet :: WWW/HTTP
Classifier: Topic :: Internet :: WWW/HTTP :: Dynamic Content
